cookiecutter.json
cookiecutter_hydro/__init__.py
cookiecutter_hydro/cli.py
hooks/post_gen_project.py
hooks/pre_gen_project.py
{{cookiecutter.project_name}}/.devcontainer/devcontainer.json
{{cookiecutter.project_name}}/.devcontainer/postCreateCommand.sh
{{cookiecutter.project_name}}/.editorconfig
{{cookiecutter.project_name}}/.github/actions/setup-poetry-env/action.yml
{{cookiecutter.project_name}}/.github/workflows/main.yml
{{cookiecutter.project_name}}/.gitignore
{{cookiecutter.project_name}}/.pre-commit-config.yaml
{{cookiecutter.project_name}}/Dockerfile
{{cookiecutter.project_name}}/LICENSE
{{cookiecutter.project_name}}/Makefile
{{cookiecutter.project_name}}/README.md
{{cookiecutter.project_name}}/poetry.toml
{{cookiecutter.project_name}}/pyproject.toml
{{cookiecutter.project_name}}/tests/test_foo.py
{{cookiecutter.project_name}}/tox.ini
{{cookiecutter.project_name}}/{{cookiecutter.project_slug}}/__init__.py
{{cookiecutter.project_name}}/{{cookiecutter.project_slug}}/data/README.md
{{cookiecutter.project_name}}/{{cookiecutter.project_slug}}/data/__init__.py
{{cookiecutter.project_name}}/{{cookiecutter.project_slug}}/data/boundaries/__init__.py
{{cookiecutter.project_name}}/{{cookiecutter.project_slug}}/data/boundaries/processed/.gitkeep
{{cookiecutter.project_name}}/{{cookiecutter.project_slug}}/data/boundaries/raw/.gitkeep
{{cookiecutter.project_name}}/{{cookiecutter.project_slug}}/data/layers/processed/.gitkeep
{{cookiecutter.project_name}}/{{cookiecutter.project_slug}}/data/layers/raw/.gitkeep
{{cookiecutter.project_name}}/{{cookiecutter.project_slug}}/data/observations/processed/.gitkeep
{{cookiecutter.project_name}}/{{cookiecutter.project_slug}}/data/observations/raw/.gitkeep
{{cookiecutter.project_name}}/{{cookiecutter.project_slug}}/notebooks/.gitkeep
{{cookiecutter.project_name}}/{{cookiecutter.project_slug}}/notebooks/README.md
{{cookiecutter.project_name}}/{{cookiecutter.project_slug}}/output/__init__.py
cookiecutter_hydro-0.0.1.dist-info/LICENSE
cookiecutter_hydro-0.0.1.dist-info/METADATA
cookiecutter_hydro-0.0.1.dist-info/WHEEL
cookiecutter_hydro-0.0.1.dist-info/entry_points.txt
cookiecutter_hydro-0.0.1.dist-info/RECORD
