Metadata-Version: 2.1
Name: cookiecutter-hydro
Version: 0.0.1
Summary: A cookiecutter template for scientific Python projects in the field of hydrology.
Home-page: https://github.com/zawadzkim/cookiecutter-hydro
Keywords: cookiecutter,template,poetry
Author: Mateusz Zawadzki
Author-email: zawadzkimat@outlook.com
Requires-Python: >=3.11,<4.0
Classifier: Programming Language :: Python :: 3
Classifier: Programming Language :: Python :: 3.11
Classifier: Programming Language :: Python :: 3.12
Requires-Dist: cookiecutter (>=2.1.1,<3.0.0)
Project-URL: Documentation, https://zawadzkim.github.io/cookiecutter-hydro/
Project-URL: Repository, https://github.com/zawadzkim/cookiecutter-hydro
